LICENSE
README.md
setup.py
jawalang/__init__.py
jawalang/__main__.py
jawalang/errorHandle.py
jawalang/print.py
jawalang/transform.py
jawalang.egg-info/PKG-INFO
jawalang.egg-info/SOURCES.txt
jawalang.egg-info/dependency_links.txt
jawalang.egg-info/entry_points.txt
jawalang.egg-info/top_level.txt