Metadata-Version: 2.1
Name: jawalang
Version: 1.0.5
Summary: Javanese programming language base on python
Home-page: https://github.com/Arsybai/jawa-language
Author: Arsybai
Author-email: me@arsybai.com
License: MIT
Keywords: programming languages,languages
License-File: LICENSE
